oneNeuronPerceptron/__init__.py
oneNeuronPerceptron/all_utils.py
oneNeuronPerceptron/perceptron.py
1NeuronPerceptron_Pypi_mdnazmulislam0087-0.0.4.dist-info/LICENSE
1NeuronPerceptron_Pypi_mdnazmulislam0087-0.0.4.dist-info/METADATA
1NeuronPerceptron_Pypi_mdnazmulislam0087-0.0.4.dist-info/WHEEL
1NeuronPerceptron_Pypi_mdnazmulislam0087-0.0.4.dist-info/top_level.txt
1NeuronPerceptron_Pypi_mdnazmulislam0087-0.0.4.dist-info/RECORD
