Metadata-Version: 2.1
Name: 1NeuronPerceptron-Pypi-mdnazmulislam0087
Version: 0.0.4
Summary: its an implimentation of Perceptron
Home-page: https://github.com/mdnazmulislam0087/1NeuronPerceptron_Pypi
Author: mdnazmulislam0087
Author-email: md.nazmul.islam0087@gmail.com
License: UNKNOWN
Project-URL: Bug Tracker, https://github.com/mdnazmulislam0087/1NeuronPerceptron_Pypi/issues
Platform: UNKNOWN
Classifier: Programming Language :: Python :: 3
Classifier: License :: OSI Approved :: MIT License
Classifier: Operating System :: OS Independent
Requires-Python: >=3.7
License-File: LICENSE
Requires-Dist: numpy
Requires-Dist: tqdm
Requires-Dist: matplotlib
Requires-Dist: pandas
Requires-Dist: joblib
